artemis/__init__.py
artemis/_artemis.cpython-312-darwin.so
artemis/artemis.py
artemis/bin/artemis_executable
artemis/bin/artemis_executable-2.0.0
artemis/cli/__init__.py
artemis/cli/main.py
artemis/etc/artemis__constants.mod
artemis/etc/artemis__io_utils_extd.mod
artemis/etc/artemis__misc_types.mod
artemis/etc/artemis__structure_cache.mod
artemis/etc/artemis__terminations.mod
artemis/etc/mod_help.mod
artemis/include/artemis.mod
artemis/lib/libartemis.a
artemis_materials-2.0.0.dev3.dist-info/METADATA
artemis_materials-2.0.0.dev3.dist-info/WHEEL
artemis_materials-2.0.0.dev3.dist-info/entry_points.txt
artemis_materials-2.0.0.dev3.dist-info/licenses/LICENSE
artemis_materials-2.0.0.dev3.dist-info/RECORD
